torcharc/__init__.py
torcharc/example/notebook/demo.py
torcharc/example/notebook/lightning_mnist.py
torcharc/example/spec/advanced/dlrm_attn.yaml
torcharc/example/spec/advanced/dlrm_sum.yaml
torcharc/example/spec/advanced/film_image_state.yaml
torcharc/example/spec/advanced/film_image_text.yaml
torcharc/example/spec/advanced/stereo_conv.yaml
torcharc/example/spec/basic/conv.yaml
torcharc/example/spec/basic/conv_lazy.yaml
torcharc/example/spec/basic/mlp.yaml
torcharc/example/spec/basic/mlp_lazy.yaml
torcharc/example/spec/basic/rnn.yaml
torcharc/example/spec/basic/stereo_conv_reuse.yaml
torcharc/example/spec/compact/conv.yaml
torcharc/example/spec/compact/conv_classifier.yaml
torcharc/example/spec/compact/mlp.yaml
torcharc/example/spec/compact/mlp_classifier.yaml
torcharc/example/spec/fn/fn_topk.yaml
torcharc/example/spec/fn/reduce_mean.yaml
torcharc/example/spec/fork/chunk.yaml
torcharc/example/spec/fork/split.yaml
torcharc/example/spec/get/get.yaml
torcharc/example/spec/get/index_select.yaml
torcharc/example/spec/get/narrow.yaml
torcharc/example/spec/graph_format/input_list.yaml
torcharc/example/spec/graph_format/input_str.yaml
torcharc/example/spec/graph_format/modules_dict.yaml
torcharc/example/spec/graph_format/modules_list_multi.yaml
torcharc/example/spec/graph_format/modules_list_single.yaml
torcharc/example/spec/graph_format/modules_nested_list.yaml
torcharc/example/spec/graph_format/modules_reuse.yaml
torcharc/example/spec/graph_format/output_dict.yaml
torcharc/example/spec/graph_format/output_list.yaml
torcharc/example/spec/graph_format/output_str.yaml
torcharc/example/spec/merge/bmm.yaml
torcharc/example/spec/merge/concat.yaml
torcharc/example/spec/merge/dot.yaml
torcharc/example/spec/merge/film.yaml
torcharc/example/spec/merge/mean.yaml
torcharc/example/spec/merge/prod.yaml
torcharc/example/spec/merge/stack.yaml
torcharc/example/spec/merge/sum.yaml
torcharc/example/spec/mnist/conv.yaml
torcharc/example/spec/mnist/mlp.yaml
torcharc-2.1.2.dist-info/METADATA
torcharc-2.1.2.dist-info/WHEEL
torcharc-2.1.2.dist-info/licenses/LICENSE
torcharc-2.1.2.dist-info/RECORD
