Metadata-Version: 2.4
Name: torcharc
Version: 2.1.2
Summary: Build PyTorch models by specifying architectures.
License-File: LICENSE
Requires-Python: >=3.12
Requires-Dist: pydantic>=2.10.4
Requires-Dist: pyyaml>=6.0.2
Provides-Extra: pytorch
Requires-Dist: tabulate>=0.9.0; extra == 'pytorch'
Requires-Dist: torch>=2.5.1; extra == 'pytorch'
Requires-Dist: torchvision>=0.20.1; extra == 'pytorch'
